leveldb/__init__.py
leveldb/_leveldb.cp311-win_amd64.pyd
leveldb/_leveldb.pyi
leveldb/_version.py
leveldb/py.typed
leveldb_py-0.0.1b0.dist-info/LICENSE
leveldb_py-0.0.1b0.dist-info/METADATA
leveldb_py-0.0.1b0.dist-info/WHEEL
leveldb_py-0.0.1b0.dist-info/top_level.txt
leveldb_py-0.0.1b0.dist-info/RECORD
